Metadata-Version: 2.1
Name: Gaussia-Binomial-Dist
Version: 0.2
Summary: Gaussian distributions
Home-page: UNKNOWN
Author: Eslam Abdelghany
Author-email: eslam322_1@hotmail.com
License: UNKNOWN
Platform: UNKNOWN
